<?xml version="1.0" encoding="utf-8"?>
<!--
  Copyright 2018 Barroux Abbey (https://www.barroux.org/)
  @author: Alexis de Lattre <alexis.delattre@akretion.com>
  License AGPL-3.0 or later (http://www.gnu.org/licenses/agpl).
-->

<odoo noupdate="1">

<record id="ochard1_parcel1" model="olive.parcel">
    <field name="ochard_id" ref="ochard1"/>
    <field name="land_registry_ref">BZ00012</field>
    <field name="area">1.5</field>
    <field name="tree_qty">100</field>
    <field name="density">8x8</field>
    <field name="variant_ids" eval="[(4, ref('variant1'))]"/>
    <field name="planted_year">2002</field>
    <field name="irrigation">dry</field>
</record>

<record id="ochard1_parcel2" model="olive.parcel">
    <field name="ochard_id" ref="ochard1"/>
    <field name="land_registry_ref">AZ00042</field>
    <field name="area">1.2</field>
    <field name="tree_qty">90</field>
    <field name="density">9x9</field>
    <field name="variant_ids" eval="[(4, ref('variant1'))]"/>
    <field name="planted_year">2003</field>
    <field name="irrigation">dry</field>
</record>

<record id="ochard1_parcel3" model="olive.parcel">
    <field name="ochard_id" ref="ochard1"/>
    <field name="land_registry_ref">CZ00015</field>
    <field name="area">2.9</field>
    <field name="tree_qty">230</field>
    <field name="density">8x8</field>
    <field name="variant_ids" eval="[(4, ref('variant2'))]"/>
    <field name="planted_year">1998</field>
    <field name="irrigation">dry</field>
</record>

<record id="ochard2_parcel1" model="olive.parcel">
    <field name="ochard_id" ref="ochard2"/>
    <field name="land_registry_ref">XZ00012</field>
    <field name="area">0.2</field>
    <field name="tree_qty">6</field>
    <field name="density">8x8</field>
    <field name="variant_ids" eval="[(4, ref('variant1'))]"/>
    <field name="planted_year">2006</field>
    <field name="irrigation">dry</field>
</record>

<record id="ochard3_parcel1" model="olive.parcel">
    <field name="ochard_id" ref="ochard3"/>
    <field name="land_registry_ref">TZ00042</field>
    <field name="area">1.1</field>
    <field name="tree_qty">50</field>
    <field name="density">8x8</field>
    <field name="variant_ids" eval="[(4, ref('variant3'))]"/>
    <field name="planted_year">2002</field>
    <field name="irrigation">dry</field>
</record>

<record id="ochard4_parcel1" model="olive.parcel">
    <field name="ochard_id" ref="ochard4"/>
    <field name="land_registry_ref">BZ00019</field>
    <field name="area">2.5</field>
    <field name="tree_qty">150</field>
    <field name="density">8x8</field>
    <field name="variant_ids" eval="[(4, ref('variant1'))]"/>
    <field name="planted_year">2002</field>
    <field name="irrigation">dry</field>
</record>

<record id="ochard5_parcel1" model="olive.parcel">
    <field name="ochard_id" ref="ochard5"/>
    <field name="land_registry_ref">RI00012</field>
    <field name="area">1.5</field>
    <field name="tree_qty">90</field>
    <field name="density">7x7</field>
    <field name="variant_ids" eval="[(4, ref('variant4'))]"/>
    <field name="planted_year">2002</field>
    <field name="irrigation">dry</field>
</record>


</odoo>
